fastapi_simple_cache/__init__.py
fastapi_simple_cache/backends/__init__.py
fastapi_simple_cache/backends/firestore.py
fastapi_simple_cache/backends/inmemory.py
fastapi_simple_cache/backends/redis.py
fastapi_simple_cache/decorator/__init__.py
fastapi_simple_cache/decorator/key_builder.py
fastapi_simple_cache-0.1.4.dist-info/LICENSE
fastapi_simple_cache-0.1.4.dist-info/WHEEL
fastapi_simple_cache-0.1.4.dist-info/METADATA
fastapi_simple_cache-0.1.4.dist-info/RECORD
