Metadata-Version: 2.1
Name: fastapi-simple-cache
Version: 0.1.4
Summary: FastAPI Simple Cache
Author-email: Sebastián Bustamante <s.bustamante.f@pm.me>
Requires-Python: >=3.7
Classifier: License :: OSI Approved :: GNU General Public License v3 or later (GPLv3+)
Classifier: Intended Audience :: Developers
Classifier: Natural Language :: English
Classifier: Programming Language :: Python :: 3
Classifier: Programming Language :: Python :: 3.7
Classifier: Programming Language :: Python :: 3.8
Classifier: Programming Language :: Python :: 3.9
Classifier: Programming Language :: Python :: 3.10
Classifier: Framework :: FastAPI
Requires-Dist: fastapi
Requires-Dist: firebase-admin ; extra == "all"
Requires-Dist: redis ; extra == "all"
Requires-Dist: pre-commit ; extra == "dev"
Requires-Dist: uvicorn ; extra == "dev"
Requires-Dist: pytest ; extra == "dev"
Requires-Dist: pytest-cov ; extra == "dev"
Requires-Dist: pytest-asyncio ; extra == "dev"
Requires-Dist: firebase-admin ; extra == "dev"
Requires-Dist: redis ; extra == "dev"
Requires-Dist: firebase-admin ; extra == "firestore"
Requires-Dist: redis ; extra == "redis"
Project-URL: Source, https://github.com/sebustam/fastapi-simple-cache
Provides-Extra: all
Provides-Extra: dev
Provides-Extra: firestore
Provides-Extra: redis
